docketanalyzer_flp/__init__.py
docketanalyzer_flp/juri.py
docketanalyzer_flp-0.0.2.dist-info/LICENSE
docketanalyzer_flp-0.0.2.dist-info/METADATA
docketanalyzer_flp-0.0.2.dist-info/WHEEL
docketanalyzer_flp-0.0.2.dist-info/top_level.txt
docketanalyzer_flp-0.0.2.dist-info/RECORD
