Metadata-Version: 2.1
Name: docketanalyzer-flp
Version: 0.0.2
Summary: Free Law Project integrations for Docket Analyzer
Home-page: https://github.com/docketanalyzer/docketanalyzer
Author: Nathan Dahlberg
License-File: LICENSE
Requires-Dist: docketanalyzer
Requires-Dist: juriscraper
